st_tabs/__init__.py
st_tabs/frontend/build/asset-manifest.json
st_tabs/frontend/build/bootstrap.min.css
st_tabs/frontend/build/index.html
st_tabs/frontend/build/static/css/main.005f19b1.css
st_tabs/frontend/build/static/css/main.005f19b1.css.map
st_tabs/frontend/build/static/js/main.25d66c2c.js
st_tabs/frontend/build/static/js/main.25d66c2c.js.LICENSE.txt
st_tabs/frontend/build/static/js/main.25d66c2c.js.map
st_tabs-0.1.1.dist-info/LICENSE
st_tabs-0.1.1.dist-info/METADATA
st_tabs-0.1.1.dist-info/WHEEL
st_tabs-0.1.1.dist-info/top_level.txt
st_tabs-0.1.1.dist-info/RECORD
